purge/__init__.py
purge/admin.py
purge/apps.py
purge/cron.py
purge/models.py
purge/settings.py
purge/tests.py
purge/urls.py
purge/wsgi.py
purge/management/__init__.py
purge/management/commands/__init__.py
purge/management/commands/purge.py
purge/migrations/0001_initial.py
purge/migrations/__init__.py
django_purge-1.0.0.dist-info/LICENSE
django_purge-1.0.0.dist-info/METADATA
django_purge-1.0.0.dist-info/WHEEL
django_purge-1.0.0.dist-info/top_level.txt
django_purge-1.0.0.dist-info/RECORD
