Metadata-Version: 2.1
Name: django-purge
Version: 1.0.0
Summary: A reusable Django app for purging database records (e.g., logs).
Home-page: https://github.com/gregschmit/django-purge
Author: Gregory N. Schmit
Author-email: gschmi4@uic.edu
License: MIT
Platform: UNKNOWN
Classifier: Environment :: Web Environment
Classifier: Framework :: Django
Classifier: Framework :: Django :: 2.0
Classifier: Intended Audience :: Developers
Classifier: License :: OSI Approved :: MIT License
Classifier: Operating System :: OS Independent
Classifier: Programming Language :: Python
Classifier: Programming Language :: Python :: 3.5
Classifier: Programming Language :: Python :: 3.6
Classifier: Topic :: Internet :: WWW/HTTP
Requires-Dist: Django (>=2)
Requires-Dist: python-dateutil
